{
  "name": "opencode-watchdog",
  "build": {
    "dockerfile": "Dockerfile"
  },
  "features": {
    "ghcr.io/shyim/devcontainers-features/bun:0": {
      "version": "1.3"
    }
  },
  "remoteUser": "vscode",
  "containerEnv": {
    "BUN_INSTALL": "/home/vscode/.bun"
  },
  "remoteEnv": {
    "PATH": "${containerEnv:PATH}:/home/vscode/.bun/bin"
  },
  "postCreateCommand": "bash .devcontainer/postCreate.sh",
  "mounts": [],
  "customizations": {
    "vscode": {
      "extensions": [
        "oven.bun-vscode",
        "esbenp.prettier-vscode"
      ]
    }
  }
}
